README.rst
setup.cfg
setup.py
labirinto/__init__.py
labirinto/admin.py
labirinto/app.py
labirinto/db.py
labirinto/modelos.py
labirinto/sala.py
labirinto_flask.egg-info/PKG-INFO
labirinto_flask.egg-info/SOURCES.txt
labirinto_flask.egg-info/dependency_links.txt
labirinto_flask.egg-info/requires.txt
labirinto_flask.egg-info/top_level.txt