Metadata-Version: 1.1
Name: labirinto-flask
Version: 0.1.1
Summary: Joguinho de labirinto usando Flask + GTM
Home-page: https://github.com/gilzoide/labirinto-flask
Author: gilzoide
Author-email: gilzoide@gmail.com
License: UNKNOWN
Platform: UNKNOWN
Classifier: Programming Language :: Python :: 2
Classifier: Development Status :: 3 - Alpha
